libfake/__init__.py
libfake/__main__.py
libfake/_version.py
libfake/cli.py
libfake/core.py
libfake/exceptions.py
libfake/formats.py
libfake/data/NAMES.DIC
libfake/data/SURNAMES.DIC
libfake-1.0.3.dist-info/licenses/LICENSE
libfake-1.0.3.dist-info/METADATA
libfake-1.0.3.dist-info/WHEEL
libfake-1.0.3.dist-info/entry_points.txt
libfake-1.0.3.dist-info/top_level.txt
libfake-1.0.3.dist-info/RECORD
