Metadata-Version: 2.4
Name: libfake
Version: 1.0.3
Summary: A professional library for generating realistic fake names and emails
Author-email: Mmdrza <Pymmdrza@gmail.com>
Maintainer-email: Mmdrza <Pymmdrza@gmail.com>
License: MIT
Project-URL: Homepage, https://github.com/libfake/libfake
Project-URL: Repository, https://github.com/libfake/libfake
Project-URL: Issues, https://github.com/libfake/libfake/issues
Project-URL: Documentation, https://github.com/libfake/libfake#readme
Keywords: fake,data,generator,names,email,testing,mock
Classifier: Development Status :: 5 - Production/Stable
Classifier: Intended Audience :: Developers
Classifier: License :: OSI Approved :: MIT License
Classifier: Programming Language :: Python :: 3
Classifier: Programming Language :: Python :: 3.8
Classifier: Programming Language :: Python :: 3.9
Classifier: Programming Language :: Python :: 3.10
Classifier: Programming Language :: Python :: 3.11
Classifier: Programming Language :: Python :: 3.12
Classifier: Topic :: Software Development :: Libraries :: Python Modules
Classifier: Topic :: Software Development :: Testing
Classifier: Topic :: Utilities
Requires-Python: >=3.8
License-File: LICENSE
Requires-Dist: rich>=10.0.0
Provides-Extra: dev
Requires-Dist: pytest>=6.0; extra == "dev"
Requires-Dist: pytest-cov>=2.10.0; extra == "dev"
Requires-Dist: black>=22.0.0; extra == "dev"
Requires-Dist: flake8>=4.0.0; extra == "dev"
Requires-Dist: mypy>=0.910; extra == "dev"
Provides-Extra: test
Requires-Dist: pytest>=6.0; extra == "test"
Requires-Dist: pytest-cov>=2.10.0; extra == "test"
Provides-Extra: lint
Requires-Dist: black>=22.0.0; extra == "lint"
Requires-Dist: flake8>=4.0.0; extra == "lint"
Requires-Dist: mypy>=0.910; extra == "lint"
Requires-Dist: isort>=5.10.0; extra == "lint"
Dynamic: license-file
